[{"car":"Plymouth","model":"Grand Voyager","pirce":"$7789.63","year":1992,"image":"https://robohash.org/solutasedpariatur.jpg?size=50x50&set=set1"},
{"car":"Maybach","model":"57","pirce":"$6738.78","year":2006,"image":"https://robohash.org/eumcommodiut.jpg?size=50x50&set=set1"},
{"car":"Chrysler","model":"PT Cruiser","pirce":"$10073.10","year":2006,"image":"https://robohash.org/recusandaequaslibero.png?size=50x50&set=set1"},
{"car":"GMC","model":"Sierra 2500","pirce":"$14311.65","year":2011,"image":"https://robohash.org/quimagnamet.jpg?size=50x50&set=set1"},
{"car":"GMC","model":"Sonoma","pirce":"$13695.71","year":1992,"image":"https://robohash.org/temporaestquas.png?size=50x50&set=set1"},
{"car":"Chevrolet","model":"Corvette","pirce":"$16408.79","year":2005,"image":"https://robohash.org/molestiaelaborumpossimus.jpg?size=50x50&set=set1"},
{"car":"Honda","model":"Insight","pirce":"$16392.31","year":2004,"image":"https://robohash.org/etisteeius.jpg?size=50x50&set=set1"},
{"car":"Audi","model":"80","pirce":"$12169.59","year":1991,"image":"https://robohash.org/doloremetmodi.jpg?size=50x50&set=set1"},
{"car":"GMC","model":"Sierra Denali","pirce":"$2958.29","year":2006,"image":"https://robohash.org/eosdebitisautem.bmp?size=50x50&set=set1"},
{"car":"Dodge","model":"Stratus","pirce":"$19750.44","year":2003,"image":"https://robohash.org/sequidolorillum.jpg?size=50x50&set=set1"},
{"car":"Ford","model":"F150","pirce":"$14236.27","year":1997,"image":"https://robohash.org/magniametiste.jpg?size=50x50&set=set1"},
{"car":"Porsche","model":"911","pirce":"$4645.79","year":2004,"image":"https://robohash.org/consequaturquasimolestiae.png?size=50x50&set=set1"},
{"car":"Pontiac","model":"GTO","pirce":"$3087.43","year":1965,"image":"https://robohash.org/repellendusiureeaque.jpg?size=50x50&set=set1"},
{"car":"Hyundai","model":"Sonata","pirce":"$6265.97","year":2005,"image":"https://robohash.org/suntetcupiditate.png?size=50x50&set=set1"},
{"car":"Nissan","model":"Murano","pirce":"$17726.75","year":2012,"image":"https://robohash.org/autemcorruptidignissimos.jpg?size=50x50&set=set1"},
{"car":"Saturn","model":"VUE","pirce":"$5312.58","year":2003,"image":"https://robohash.org/molestiaenobispraesentium.bmp?size=50x50&set=set1"},
{"car":"Dodge","model":"Ram 1500","pirce":"$10450.07","year":2004,"image":"https://robohash.org/etconsequaturcumque.png?size=50x50&set=set1"},
{"car":"Buick","model":"Reatta","pirce":"$3398.72","year":1990,"image":"https://robohash.org/dignissimosvoluptatibusiste.jpg?size=50x50&set=set1"},
{"car":"Pontiac","model":"Grand Prix","pirce":"$9550.60","year":1991,"image":"https://robohash.org/aperiamducimusexercitationem.bmp?size=50x50&set=set1"},
{"car":"Chevrolet","model":"Tahoe","pirce":"$16556.24","year":1996,"image":"https://robohash.org/eavelitesse.jpg?size=50x50&set=set1"},
{"car":"Chevrolet","model":"Silverado 1500","pirce":"$6670.29","year":2000,"image":"https://robohash.org/atqueetsoluta.bmp?size=50x50&set=set1"},
{"car":"Subaru","model":"Legacy","pirce":"$17218.74","year":1989,"image":"https://robohash.org/sintipsumdoloribus.png?size=50x50&set=set1"},
{"car":"Dodge","model":"Caliber","pirce":"$7651.34","year":2011,"image":"https://robohash.org/ipsadoloremminima.png?size=50x50&set=set1"},
{"car":"Ford","model":"Explorer Sport Trac","pirce":"$9172.68","year":2006,"image":"https://robohash.org/dolorautiure.png?size=50x50&set=set1"},
{"car":"Jeep","model":"Patriot","pirce":"$8197.57","year":2009,"image":"https://robohash.org/autvelitodio.bmp?size=50x50&set=set1"},
{"car":"Audi","model":"200","pirce":"$2413.44","year":1989,"image":"https://robohash.org/errorfugitmollitia.png?size=50x50&set=set1"},
{"car":"Chevrolet","model":"Tahoe","pirce":"$11938.55","year":1995,"image":"https://robohash.org/nihilbeataedolores.bmp?size=50x50&set=set1"},
{"car":"Chevrolet","model":"Express 3500","pirce":"$14960.69","year":2005,"image":"https://robohash.org/doloremrerumnihil.jpg?size=50x50&set=set1"},
{"car":"Toyota","model":"Tacoma","pirce":"$12350.30","year":1998,"image":"https://robohash.org/aliasutfugit.png?size=50x50&set=set1"},
{"car":"Audi","model":"S8","pirce":"$19618.41","year":2007,"image":"https://robohash.org/officiaiustoet.jpg?size=50x50&set=set1"}]